seqlearner/Embedding.py
seqlearner/EmbeddingHyperOptimization.py
seqlearner/EmbeddingLoader.py
seqlearner/Freq2Vec.py
seqlearner/GensimWord2Vec.py
seqlearner/MultiTaskLearner.py
seqlearner/PseudoLabeler.py
seqlearner/SemiSupervisedLearner.py
seqlearner/Sent2Vec.py
seqlearner/SkipGram.py
seqlearner/WordEmbedder.py
seqlearner/__init__.py
seqlearner/aux.py
seqlearner/test.py
seqlearner/test2.py
seqlearner/tester.py
seqlearner/examples/__init__.py
seqlearner/examples/train_uniprot.py
seqlearner/fastText/__init__.py
seqlearner/fastText/tweetTokenize.py
seqlearner/fastText/wikiTokenize.py
seqlearner/fastText/src/__init__.py
seqlearner/fastText/src/setup.py
seqlearner/semisup/__init__.py
seqlearner/semisup/setup.py
seqlearner/semisup/examples/__init__.py
seqlearner/semisup/examples/compare_gaussian_methods.py
seqlearner/semisup/examples/compare_linsvm_methods.py
seqlearner/semisup/examples/compare_rbfsvm_methods.py
seqlearner/semisup/examples/example.py
seqlearner/semisup/examples/plotutils.py
seqlearner/semisup/frameworks/CPLELearning.py
seqlearner/semisup/frameworks/SelfLearning.py
seqlearner/semisup/frameworks/__init__.py
seqlearner/semisup/methods/__init__.py
seqlearner/semisup/methods/qns3vm.py
seqlearner/semisup/methods/scikitTSVM.py
seqlearner/semisup/methods/scikitWQDA.py
seqlearner-0.0.7.dist-info/METADATA
seqlearner-0.0.7.dist-info/RECORD
seqlearner-0.0.7.dist-info/WHEEL
seqlearner-0.0.7.dist-info/top_level.txt
