Metadata-Version: 2.1
Name: seqlearner
Version: 0.0.7
Summary: The multitask learning package for semi-supervised learning on biological sequences
Home-page: https://github.com/EliHei/SeqLearner
Author: Elyas Heidari, Mohsen Naghipourfar
Author-email: almasmadani@gmail.com, mn7697np@gmail.com
License: MIT
Platform: UNKNOWN
Classifier: Programming Language :: Python :: 3
Classifier: License :: OSI Approved :: MIT License
Classifier: Operating System :: OS Independent
